{
  "name": "puppetlabs-ntp",
  "version": "4.2.0",
  "author": "Puppet Labs",
  "summary": "Installs, configures, and manages the NTP service.",
  "license": "Apache-2.0",
  "source": "https://github.com/puppetlabs/puppetlabs-ntp",
  "project_page": "https://github.com/puppetlabs/puppetlabs-ntp",
  "issues_url": "https://tickets.puppetlabs.com/browse/MODULES",
  "dependencies": [
    {"name":"puppetlabs/stdlib","version_requirement":">= 4.6.0 < 5.0.0"}
  ],
  "data_provider": null,
  "operatingsystem_support": [
    {
      "operatingsystem": "RedHat",
      "operatingsystemrelease": [
        "5",
        "6",
        "7"
      ]
    },
    {
      "operatingsystem": "CentOS",
      "operatingsystemrelease": [
        "5",
        "6",
        "7"
      ]
    },
    {
      "operatingsystem": "OracleLinux",
      "operatingsystemrelease": [
        "5",
        "6",
        "7"
      ]
    },
    {
      "operatingsystem": "Scientific",
      "operatingsystemrelease": [
        "5",
        "6",
        "7"
      ]
    },
    {
      "operatingsystem": "Fedora",
      "operatingsystemrelease": [
        "20",
        "21",
        "22"
      ]
    },
    {
      "operatingsystem": "SLES",
      "operatingsystemrelease": [
        "10 SP4",
        "11 SP1",
        "12"
      ]
    },
    {
      "operatingsystem": "Debian",
      "operatingsystemrelease": [
        "6",
        "7",
        "8"
      ]
    },
    {
      "operatingsystem": "Ubuntu",
      "operatingsystemrelease": [
        "10.04",
        "12.04",
        "14.04"
      ]
    },
    {
      "operatingsystem": "Solaris",
      "operatingsystemrelease": [
        "11"
      ]
    },
    {
      "operatingsystem": "AIX",
      "operatingsystemrelease": [
        "5.3",
        "6.1",
        "7.1"
      ]
    },
    {
      "operatingsystem": "Amazon",
      "operatingsystemrelease": [
        "2013.09",
        "2014.03",
        "2014.09",
        "2015.03"
      ]
    }
  ],
  "requirements": [
    {
      "name": "pe",
      "version_requirement": ">= 3.7.0 < 2015.4.0"
    },
    {
      "name": "puppet",
      "version_requirement": ">= 3.0.0 < 5.0.0"
    }
  ],
  "description": "NTP Module for Debian, Ubuntu, CentOS, RHEL, OEL, Fedora, FreeBSD, ArchLinux, Amazon Linux and Gentoo."
}
